.gitignore
Gruntfile.js
MANIFEST.in
Makefile
README.txt
bump-versions.py
package-lock.json
package.json
setup.cfg
setup.py
castle/__init__.py
castle.theme.egg-info/PKG-INFO
castle.theme.egg-info/SOURCES.txt
castle.theme.egg-info/dependency_links.txt
castle.theme.egg-info/entry_points.txt
castle.theme.egg-info/namespace_packages.txt
castle.theme.egg-info/not-zip-safe
castle.theme.egg-info/requires.txt
castle.theme.egg-info/top_level.txt
castle/theme/__init__.py
castle/theme/configure.zcml
castle/theme/interfaces.py
castle/theme/locales/README.txt
castle/theme/profiles/default/browserlayer.xml
castle/theme/profiles/default/metadata.xml
castle/theme/profiles/default/registry.xml
castle/theme/profiles/default/theme.xml
castle/theme/theme_resources/.gitignore
castle/theme/theme_resources/frontpage.html
castle/theme/theme_resources/index.html
castle/theme/theme_resources/manifest.cfg
castle/theme/theme_resources/page.html
castle/theme/theme_resources/preview.png
castle/theme/theme_resources/css/app.css
castle/theme/theme_resources/css/build-compiled.css.map
castle/theme/theme_resources/css/custom-variables.less
castle/theme/theme_resources/css/frontpage.css
castle/theme/theme_resources/css/frontpage.less
castle/theme/theme_resources/css/plone.css
castle/theme/theme_resources/css/plone.less
castle/theme/theme_resources/css/theme.css
castle/theme/theme_resources/css/theme.less
castle/theme/theme_resources/css/bootstrap/alerts.less
castle/theme/theme_resources/css/bootstrap/badges.less
castle/theme/theme_resources/css/bootstrap/bootstrap.less
castle/theme/theme_resources/css/bootstrap/breadcrumbs.less
castle/theme/theme_resources/css/bootstrap/button-groups.less
castle/theme/theme_resources/css/bootstrap/buttons.less
castle/theme/theme_resources/css/bootstrap/carousel.less
castle/theme/theme_resources/css/bootstrap/close.less
castle/theme/theme_resources/css/bootstrap/code.less
castle/theme/theme_resources/css/bootstrap/component-animations.less
castle/theme/theme_resources/css/bootstrap/dropdowns.less
castle/theme/theme_resources/css/bootstrap/forms.less
castle/theme/theme_resources/css/bootstrap/grid.less
castle/theme/theme_resources/css/bootstrap/input-groups.less
castle/theme/theme_resources/css/bootstrap/jumbotron.less
