Metadata-Version: 1.1
Name: castle.theme
Version: 1.0.5
Summary: CastleCMS Theme Package
Home-page: https://github.com/castlecms/castle.theme
Author: Wildcard Corp.
Author-email: info@wildcardcorp.com
License: GPL
Platform: UNKNOWN
Classifier: Framework :: Plone
Classifier: Framework :: Plone :: 5.0
Classifier: Framework :: Plone :: 5.1
Classifier: Programming Language :: Python
Classifier: Topic :: Software Development :: Libraries :: Python Modules
